{
    "id": 11998,
    "name": "Spindel",
    "last_updated": "2023-08-03",
    "incomplete": true,
    "members": true,
    "release_date": "2023-01-25",
    "combat_level": 302,
    "size": 4,
    "hitpoints": 515,
    "max_hit": 14,
    "attack_type": [
        "stab",
        "ranged",
        "magic"
    ],
    "attack_speed": 4,
    "aggressive": true,
    "poisonous": false,
    "venomous": false,
    "immune_poison": false,
    "immune_venom": false,
    "attributes": [],
    "category": [
        "spiders",
        "bosses"
    ],
    "slayer_monster": true,
    "slayer_level": 1,
    "slayer_xp": 541.0,
    "slayer_masters": [
        "turael",
        "spria",
        "krystilia",
        "konar",
        "nieve",
        "duradel"
    ],
    "duplicate": false,
    "examine": "It's more scared of you than you are of it... right?",
    "wiki_name": "Spindel",
    "wiki_url": "https://oldschool.runescape.wiki/w/Spindel",
    "attack_level": 200,
    "strength_level": 130,
    "defence_level": 225,
    "magic_level": 235,
    "ranged_level": 286,
    "attack_bonus": 0,
    "strength_bonus": 0,
    "attack_magic": 0,
    "magic_bonus": 0,
    "attack_ranged": 0,
    "ranged_bonus": 0,
    "defence_stab": 70,
    "defence_slash": 70,
    "defence_crush": 10,
    "defence_magic": 205,
    "defence_ranged": 103,
    "drops": []
}